pyolia/client.py
pyolia-0.4.0.dist-info/LICENSE
pyolia-0.4.0.dist-info/METADATA
pyolia-0.4.0.dist-info/WHEEL
pyolia-0.4.0.dist-info/RECORD
