Metadata-Version: 2.1
Name: pyolia
Version: 0.4.0
Summary: Async Python wrapper to interact with internal Veolia API
Home-page: https://github.com/tetienne/python-veolia-api/
License: MIT
Author: Thibaut Etienne
Requires-Python: >=3.8.1,<4.0
Classifier: License :: OSI Approved :: MIT License
Classifier: Programming Language :: Python :: 3
Classifier: Programming Language :: Python :: 3.9
Classifier: Programming Language :: Python :: 3.10
Classifier: Programming Language :: Python :: 3.11
Classifier: Programming Language :: Python :: 3.12
Requires-Dist: aiohttp (>=3.8.1)
Requires-Dist: backoff (>=2.2.1,<3.0.0)
Project-URL: Repository, https://github.com/tetienne/python-veolia-api/
